{"books":[
  {
    "title": "Anna Karenina",
    "author": "Leo Tolstoy",
    "date": "1982-07-82",
    "img": " none",
    "id": "00001A"
  },
  {
    "title": "Madame Bovary",
    "author": "Gustave Flaubert",
    "date": "1982-07-.83",
    "img": " none",
    "id": "00001B"
  },
  {
    "title": "War and Peace",
    "author": "Leo Tolstoy",
    "date": "1982-07-84",
    "img": " none",
    "id": "00001C"
  },
  {
    "title": "The Great Gatsby",
    "author": "F. Scott Fitzgerald",
    "date": "1982-07-85",
    "img": " none",
    "id": "00001D"
  },
  {
    "title": "Lolita",
    "author": "Vladimir Nabokov",
    "date": "1982-07-85",
    "img": " none",
    "id": "00001E"
  },
  {
    "title": "Middlemarch ",
    "author": "George Eliot",
    "date": "1982-07-85",
    "img": " none",
    "id": "00001F"
  },
  {
    "title": "The Adventures of Huckleberry Finn",
    "author": "Mark Twain",
    "date": "1982-07-85",
    "img": " none",
    "id": "00002A"
  },
  {
    "title": "The Stories of Anton Chekhov",
    "author": "Anton Chekhov",
    "date": "1982-07-85",
    "img": " none",
    "id": "00002B"
  },
  {
    "title": "In Search of Lost Time",
    "author": "Marcel Proust",
    "date": "1982-07-85",
    "img": " none",
    "id": "00002C"
  }
]}